gh_toolkit/__init__.py
gh_toolkit/cli.py
gh_toolkit/types.py
gh_toolkit/commands/__init__.py
gh_toolkit/commands/invite.py
gh_toolkit/commands/page.py
gh_toolkit/commands/repo.py
gh_toolkit/commands/site.py
gh_toolkit/commands/tag.py
gh_toolkit/commands/transfer.py
gh_toolkit/core/__init__.py
gh_toolkit/core/github_client.py
gh_toolkit/core/health_checker.py
gh_toolkit/core/page_generator.py
gh_toolkit/core/repo_cloner.py
gh_toolkit/core/repo_extractor.py
gh_toolkit/core/site_generator.py
gh_toolkit/core/topic_tagger.py
gh_toolkit/utils/__init__.py
gh_toolkit-0.10.3.dist-info/METADATA
gh_toolkit-0.10.3.dist-info/WHEEL
gh_toolkit-0.10.3.dist-info/entry_points.txt
gh_toolkit-0.10.3.dist-info/RECORD
